zerox/__init__.py
zerox/utils.py
zerox-0.0.1.dist-info/LICENSE
zerox-0.0.1.dist-info/WHEEL
zerox-0.0.1.dist-info/METADATA
zerox-0.0.1.dist-info/RECORD
