Metadata-Version: 2.1
Name: zerox
Version: 0.0.1
Summary: Paper - Pytorch
Home-page: https://github.com/kyegomez/paper
License: MIT
Keywords: artificial intelligence,deep learning,optimizers,Prompt Engineering
Author: Kye Gomez
Author-email: kye@apac.ai
Requires-Python: >=3.6,<4.0
Classifier: Development Status :: 4 - Beta
Classifier: Intended Audience :: Developers
Classifier: License :: OSI Approved :: MIT License
Classifier: Programming Language :: Python :: 3
Classifier: Programming Language :: Python :: 3.6
Classifier: Programming Language :: Python :: 3.7
Classifier: Programming Language :: Python :: 3.8
Classifier: Programming Language :: Python :: 3.9
Classifier: Programming Language :: Python :: 3.10
Classifier: Programming Language :: Python :: 3.11
Classifier: Programming Language :: Python :: 3.9
Classifier: Topic :: Scientific/Engineering :: Artificial Intelligence
Requires-Dist: fastapi (>=0.68.0,<0.69.0)
Requires-Dist: httpx (>=0.19.0,<0.20.0)
Requires-Dist: pydantic (>=1.9.0,<2.0.0)
Requires-Dist: uvicorn (>=0.15.0,<0.16.0)
Project-URL: Documentation, https://github.com/kyegomez/paper
Project-URL: Repository, https://github.com/kyegomez/paper
